[
  {
    "BookID": 1,
    "Title": "Uni",
    "Author": "Walters Knight",
    "ISBN": "2,979",
    "CheckedOut": true,
    "DateDueBck": "",
    "UserID": null
  },
  {
    "BookID": 2,
    "Title": "Prosely",
    "Author": "Parker Dickson",
    "ISBN": "1,386",
    "CheckedOut": true,
    "DateDueBck": "",
    "UserID": null
  },
  {
    "BookID": 3,
    "Title": "Zerbina",
    "Author": "Knowles Stevens",
    "ISBN": "3,135",
    "CheckedOut": false,
    "DateDueBck": "",
    "UserID": null
  },
  {
    "BookID": 4,
    "Title": "Printspan",
    "Author": "Bernice Carroll",
    "ISBN": "1,517",
    "CheckedOut": false,
    "DateDueBck": "",
    "UserID": null
  },
  {
    "BookID": 5,
    "Title": "Jetsilk",
    "Author": "Trina Bright",
    "ISBN": "1,976",
    "CheckedOut": false,
    "DateDueBck": "",
    "UserID": null
  },
  {
    "BookID": 6,
    "Title": "Shadease",
    "Author": "Ramos Conley",
    "ISBN": "3,528",
    "CheckedOut": false,
    "DateDueBck": "",
    "UserID": null
  },
  {
    "BookID": 7,
    "Title": "Exodoc",
    "Author": "Golden Branch",
    "ISBN": "3,326",
    "CheckedOut": true,
    "DateDueBck": "",
    "UserID": null
  },
  {
    "BookID": 8,
    "Title": "Gronk",
    "Author": "Lott Mullen",
    "ISBN": "3,936",
    "CheckedOut": false,
    "DateDueBck": "",
    "UserID": null
  },
  {
    "BookID": 9,
    "Title": "Snacktion",
    "Author": "Stout Banks",
    "ISBN": "1,181",
    "CheckedOut": true,
    "DateDueBck": "",
    "UserID": null
  },
  {
    "BookID": 10,
    "Title": "Centree",
    "Author": "Mcdowell Humphrey",
    "ISBN": "1,571",
    "CheckedOut": true,
    "DateDueBck": "",
    "UserID": null
  },
  {
    "BookID": 11,
    "Title": "Zaphire",
    "Author": "Banks Martin",
    "ISBN": "3,339",
    "CheckedOut": true,
    "DateDueBck": "",
    "UserID": null
  },
  {
    "BookID": 12,
    "Title": "Idetica",
    "Author": "Sabrina Mooney",
    "ISBN": "2,975",
    "CheckedOut": true,
    "DateDueBck": "",
    "UserID": null
  },
  {
    "BookID": 13,
    "Title": "Straloy",
    "Author": "Delacruz Stanley",
    "ISBN": "2,223",
    "CheckedOut": true,
    "DateDueBck": "",
    "UserID": null
  },
  {
    "BookID": 14,
    "Title": "Extragen",
    "Author": "Velez Suarez",
    "ISBN": "3,161",
    "CheckedOut": true,
    "DateDueBck": "",
    "UserID": null
  },
  {
    "BookID": 15,
    "Title": "Photobin",
    "Author": "Morrow Rodriquez",
    "ISBN": "2,445",
    "CheckedOut": true,
    "DateDueBck": "",
    "UserID": null
  },
  {
    "BookID": 16,
    "Title": "Fishland",
    "Author": "Briggs Caldwell",
    "ISBN": "3,735",
    "CheckedOut": true,
    "DateDueBck": "",
    "UserID": null
  },
  {
    "BookID": 17,
    "Title": "Biohab",
    "Author": "Gilliam Harrington",
    "ISBN": "1,815",
    "CheckedOut": false,
    "DateDueBck": "",
    "UserID": null
  },
  {
    "BookID": 18,
    "Title": "Zytrex",
    "Author": "Rhonda Head",
    "ISBN": "1,256",
    "CheckedOut": false,
    "DateDueBck": "",
    "UserID": null
  },
  {
    "BookID": 19,
    "Title": "Zentime",
    "Author": "Shaffer Buchanan",
    "ISBN": "1,346",
    "CheckedOut": true,
    "DateDueBck": "",
    "UserID": null
  },
  {
    "BookID": 20,
    "Title": "Viagreat",
    "Author": "Kara Campbell",
    "ISBN": "2,760",
    "CheckedOut": true,
    "DateDueBck": "",
    "UserID": null
  },
  {
    "BookID": 21,
    "Title": "Orbixtar",
    "Author": "Terrie Bush",
    "ISBN": "2,913",
    "CheckedOut": false,
    "DateDueBck": "",
    "UserID": null
  },
  {
    "BookID": 22,
    "Title": "Accidency",
    "Author": "Bernadine Hutchinson",
    "ISBN": "2,870",
    "CheckedOut": true,
    "DateDueBck": "",
    "UserID": null
  },
  {
    "BookID": 23,
    "Title": "Icology",
    "Author": "Albert Mathews",
    "ISBN": "1,136",
    "CheckedOut": true,
    "DateDueBck": "",
    "UserID": null
  },
  {
    "BookID": 24,
    "Title": "Circum",
    "Author": "Nellie Flynn",
    "ISBN": "2,584",
    "CheckedOut": true,
    "DateDueBck": "",
    "UserID": null
  },
  {
    "BookID": 25,
    "Title": "Ronbert",
    "Author": "Harvey Carson",
    "ISBN": "1,014",
    "CheckedOut": false,
    "DateDueBck": "",
    "UserID": null
  },
  {
    "BookID": 26,
    "Title": "Pyrami",
    "Author": "Rowland Owens",
    "ISBN": "3,966",
    "CheckedOut": true,
    "DateDueBck": "",
    "UserID": null
  },
  {
    "BookID": 27,
    "Title": "Softmicro",
    "Author": "Little Coffey",
    "ISBN": "3,227",
    "CheckedOut": false,
    "DateDueBck": "",
    "UserID": null
  },
  {
    "BookID": 28,
    "Title": "Polarium",
    "Author": "English Mccormick",
    "ISBN": "2,705",
    "CheckedOut": true,
    "DateDueBck": "",
    "UserID": null
  },
  {
    "BookID": 29,
    "Title": "Magnafone",
    "Author": "Evangeline Harrell",
    "ISBN": "2,610",
    "CheckedOut": true,
    "DateDueBck": "",
    "UserID": null
  },
  {
    "BookID": 30,
    "Title": "Macronaut",
    "Author": "Savage Dorsey",
    "ISBN": "1,452",
    "CheckedOut": true,
    "DateDueBck": "",
    "UserID": null
  },
  {
    "BookID": 31,
    "Title": "Kindaloo",
    "Author": "Hewitt Adkins",
    "ISBN": "2,617",
    "CheckedOut": false,
    "DateDueBck": "",
    "UserID": null
  },
  {
    "BookID": 32,
    "Title": "Isostream",
    "Author": "Lucia Sanchez",
    "ISBN": "1,291",
    "CheckedOut": true,
    "DateDueBck": "",
    "UserID": null
  },
  {
    "BookID": 33,
    "Title": "Digigen",
    "Author": "Petty Kennedy",
    "ISBN": "1,401",
    "CheckedOut": true,
    "DateDueBck": "",
    "UserID": null
  },
  {
    "BookID": 34,
    "Title": "Bedlam",
    "Author": "Hanson Houston",
    "ISBN": "2,317",
    "CheckedOut": true,
    "DateDueBck": "",
    "UserID": null
  },
  {
    "BookID": 35,
    "Title": "Exoteric",
    "Author": "Bush Haynes",
    "ISBN": "3,904",
    "CheckedOut": true,
    "DateDueBck": "",
    "UserID": null
  },
  {
    "BookID": 36,
    "Title": "Multiflex",
    "Author": "Harmon Willis",
    "ISBN": "3,551",
    "CheckedOut": true,
    "DateDueBck": "",
    "UserID": null
  },
  {
    "BookID": 37,
    "Title": "Austex",
    "Author": "Rene Steele",
    "ISBN": "1,849",
    "CheckedOut": false,
    "DateDueBck": "",
    "UserID": null
  },
  {
    "BookID": 38,
    "Title": "Sloganaut",
    "Author": "Roxanne Trevino",
    "ISBN": "3,440",
    "CheckedOut": true,
    "DateDueBck": "",
    "UserID": null
  },
  {
    "BookID": 39,
    "Title": "Tsunamia",
    "Author": "Rasmussen Campos",
    "ISBN": "1,040",
    "CheckedOut": true,
    "DateDueBck": "",
    "UserID": null
  },
  {
    "BookID": 40,
    "Title": "Xinware",
    "Author": "Day Armstrong",
    "ISBN": "1,271",
    "CheckedOut": true,
    "DateDueBck": "",
    "UserID": null
  },
  {
    "BookID": 41,
    "Title": "Permadyne",
    "Author": "Dyer Gilliam",
    "ISBN": "2,026",
    "CheckedOut": false,
    "DateDueBck": "",
    "UserID": null
  },
  {
    "BookID": 42,
    "Title": "Kongle",
    "Author": "Aida Goodman",
    "ISBN": "2,659",
    "CheckedOut": false,
    "DateDueBck": "",
    "UserID": null
  },
  {
    "BookID": 43,
    "Title": "Sportan",
    "Author": "Williamson Sweet",
    "ISBN": "3,738",
    "CheckedOut": false,
    "DateDueBck": "",
    "UserID": null
  },
  {
    "BookID": 44,
    "Title": "Cubix",
    "Author": "Manuela Velez",
    "ISBN": "3,957",
    "CheckedOut": true,
    "DateDueBck": "",
    "UserID": null
  },
  {
    "BookID": 45,
    "Title": "Enersol",
    "Author": "Lynn Fry",
    "ISBN": "2,292",
    "CheckedOut": false,
    "DateDueBck": "",
    "UserID": null
  },
  {
    "BookID": 46,
    "Title": "Insectus",
    "Author": "Dominguez Soto",
    "ISBN": "2,387",
    "CheckedOut": true,
    "DateDueBck": "",
    "UserID": null
  },
  {
    "BookID": 47,
    "Title": "Colaire",
    "Author": "Mccray Rodriguez",
    "ISBN": "2,402",
    "CheckedOut": true,
    "DateDueBck": "",
    "UserID": null
  },
  {
    "BookID": 48,
    "Title": "Zilodyne",
    "Author": "Ruthie Mccullough",
    "ISBN": "2,656",
    "CheckedOut": false,
    "DateDueBck": "",
    "UserID": null
  },
  {
    "BookID": 49,
    "Title": "Verbus",
    "Author": "Aguilar Hester",
    "ISBN": "2,556",
    "CheckedOut": false,
    "DateDueBck": "",
    "UserID": null
  },
  {
    "BookID": 50,
    "Title": "Exostream",
    "Author": "Dickerson Phillips",
    "ISBN": "3,543",
    "CheckedOut": false,
    "DateDueBck": "",
    "UserID": null
  },
  {
    "BookID": 51,
    "Title": "Isoplex",
    "Author": "Helene Pitts",
    "ISBN": "2,111",
    "CheckedOut": true,
    "DateDueBck": "",
    "UserID": null
  },
  {
    "BookID": 52,
    "Title": "Peticular",
    "Author": "Teri Graham",
    "ISBN": "2,633",
    "CheckedOut": false,
    "DateDueBck": "",
    "UserID": null
  },
  {
    "BookID": 53,
    "Title": "Ecosys",
    "Author": "Karin Potts",
    "ISBN": "3,216",
    "CheckedOut": false,
    "DateDueBck": "",
    "UserID": null
  },
  {
    "BookID": 54,
    "Title": "Netbook",
    "Author": "Carla Schroeder",
    "ISBN": "2,331",
    "CheckedOut": false,
    "DateDueBck": "",
    "UserID": null
  },
  {
    "BookID": 55,
    "Title": "Eternis",
    "Author": "Barbara Bray",
    "ISBN": "2,939",
    "CheckedOut": true,
    "DateDueBck": "",
    "UserID": null
  },
  {
    "BookID": 56,
    "Title": "Synkgen",
    "Author": "Effie Davis",
    "ISBN": "1,221",
    "CheckedOut": false,
    "DateDueBck": "",
    "UserID": null
  },
  {
    "BookID": 57,
    "Title": "Bluplanet",
    "Author": "Preston Knox",
    "ISBN": "1,800",
    "CheckedOut": false,
    "DateDueBck": "",
    "UserID": null
  },
  {
    "BookID": 58,
    "Title": "Renovize",
    "Author": "Whitehead Kline",
    "ISBN": "3,528",
    "CheckedOut": true,
    "DateDueBck": "",
    "UserID": null
  },
  {
    "BookID": 59,
    "Title": "Avit",
    "Author": "Mcgowan Conway",
    "ISBN": "1,288",
    "CheckedOut": false,
    "DateDueBck": "",
    "UserID": null
  },
  {
    "BookID": 60,
    "Title": "Kangle",
    "Author": "Guerra Bates",
    "ISBN": "1,683",
    "CheckedOut": true,
    "DateDueBck": "",
    "UserID": null
  },
  {
    "BookID": 61,
    "Title": "Noralex",
    "Author": "Leona Horn",
    "ISBN": "3,314",
    "CheckedOut": false,
    "DateDueBck": "",
    "UserID": null
  },
  {
    "BookID": 62,
    "Title": "Kidgrease",
    "Author": "Wilma Robertson",
    "ISBN": "3,561",
    "CheckedOut": true,
    "DateDueBck": "",
    "UserID": null
  },
  {
    "BookID": 63,
    "Title": "Signity",
    "Author": "Barlow Ingram",
    "ISBN": "3,944",
    "CheckedOut": true,
    "DateDueBck": "",
    "UserID": null
  },
  {
    "BookID": 64,
    "Title": "Quantasis",
    "Author": "Jessie Wolfe",
    "ISBN": "2,307",
    "CheckedOut": true,
    "DateDueBck": "",
    "UserID": null
  },
  {
    "BookID": 65,
    "Title": "Zenolux",
    "Author": "Sawyer Curtis",
    "ISBN": "2,975",
    "CheckedOut": true,
    "DateDueBck": "",
    "UserID": null
  },
  {
    "BookID": 66,
    "Title": "Primordia",
    "Author": "Leigh Copeland",
    "ISBN": "2,231",
    "CheckedOut": true,
    "DateDueBck": "",
    "UserID": null
  },
  {
    "BookID": 67,
    "Title": "Zidox",
    "Author": "Solis Robles",
    "ISBN": "2,107",
    "CheckedOut": false,
    "DateDueBck": "",
    "UserID": null
  },
  {
    "BookID": 68,
    "Title": "Speedbolt",
    "Author": "Reed Mullins",
    "ISBN": "2,271",
    "CheckedOut": true,
    "DateDueBck": "",
    "UserID": null
  },
  {
    "BookID": 69,
    "Title": "Isosphere",
    "Author": "Ferguson Henson",
    "ISBN": "2,757",
    "CheckedOut": false,
    "DateDueBck": "",
    "UserID": null
  },
  {
    "BookID": 70,
    "Title": "Quadeebo",
    "Author": "Cathy Daniels",
    "ISBN": "3,447",
    "CheckedOut": true,
    "DateDueBck": "",
    "UserID": null
  },
  {
    "BookID": 71,
    "Title": "Quizmo",
    "Author": "Joy Delacruz",
    "ISBN": "1,244",
    "CheckedOut": true,
    "DateDueBck": "",
    "UserID": null
  },
  {
    "BookID": 72,
    "Title": "Elentrix",
    "Author": "Valarie Shields",
    "ISBN": "2,849",
    "CheckedOut": false,
    "DateDueBck": "",
    "UserID": null
  },
  {
    "BookID": 73,
    "Title": "Entality",
    "Author": "Gibbs Odonnell",
    "ISBN": "1,894",
    "CheckedOut": true,
    "DateDueBck": "",
    "UserID": null
  },
  {
    "BookID": 74,
    "Title": "Equicom",
    "Author": "Cathleen Ortega",
    "ISBN": "2,913",
    "CheckedOut": false,
    "DateDueBck": "",
    "UserID": null
  },
  {
    "BookID": 75,
    "Title": "Vixo",
    "Author": "Mayer Randolph",
    "ISBN": "1,123",
    "CheckedOut": true,
    "DateDueBck": "",
    "UserID": null
  },
  {
    "BookID": 76,
    "Title": "Krag",
    "Author": "Jensen Diaz",
    "ISBN": "1,756",
    "CheckedOut": true,
    "DateDueBck": "",
    "UserID": null
  },
  {
    "BookID": 77,
    "Title": "Avenetro",
    "Author": "Traci Dillon",
    "ISBN": "3,703",
    "CheckedOut": false,
    "DateDueBck": "",
    "UserID": null
  },
  {
    "BookID": 78,
    "Title": "Teraprene",
    "Author": "Valdez Keith",
    "ISBN": "3,619",
    "CheckedOut": false,
    "DateDueBck": "",
    "UserID": null
  },
  {
    "BookID": 79,
    "Title": "Waterbaby",
    "Author": "Vincent Grant",
    "ISBN": "3,689",
    "CheckedOut": false,
    "DateDueBck": "",
    "UserID": null
  },
  {
    "BookID": 80,
    "Title": "Netplode",
    "Author": "Talley Cervantes",
    "ISBN": "1,328",
    "CheckedOut": true,
    "DateDueBck": "",
    "UserID": null
  },
  {
    "BookID": 81,
    "Title": "Animalia",
    "Author": "Yvonne Emerson",
    "ISBN": "2,557",
    "CheckedOut": true,
    "DateDueBck": "",
    "UserID": null
  },
  {
    "BookID": 82,
    "Title": "Techade",
    "Author": "Todd Hartman",
    "ISBN": "3,314",
    "CheckedOut": true,
    "DateDueBck": "",
    "UserID": null
  },
  {
    "BookID": 83,
    "Title": "Callflex",
    "Author": "Kim Baldwin",
    "ISBN": "1,066",
    "CheckedOut": false,
    "DateDueBck": "",
    "UserID": null
  },
  {
    "BookID": 84,
    "Title": "Ezent",
    "Author": "Lloyd Rowland",
    "ISBN": "3,128",
    "CheckedOut": false,
    "DateDueBck": "",
    "UserID": null
  },
  {
    "BookID": 85,
    "Title": "Utara",
    "Author": "Tanisha Richard",
    "ISBN": "1,021",
    "CheckedOut": false,
    "DateDueBck": "",
    "UserID": null
  },
  {
    "BookID": 86,
    "Title": "Biflex",
    "Author": "Hatfield Jimenez",
    "ISBN": "3,390",
    "CheckedOut": true,
    "DateDueBck": "",
    "UserID": null
  },
  {
    "BookID": 87,
    "Title": "Marketoid",
    "Author": "Constance Moon",
    "ISBN": "3,144",
    "CheckedOut": true,
    "DateDueBck": "",
    "UserID": null
  },
  {
    "BookID": 88,
    "Title": "Enaut",
    "Author": "Jill Owen",
    "ISBN": "1,542",
    "CheckedOut": false,
    "DateDueBck": "",
    "UserID": null
  },
  {
    "BookID": 89,
    "Title": "Furnitech",
    "Author": "Duncan Cherry",
    "ISBN": "2,691",
    "CheckedOut": true,
    "DateDueBck": "",
    "UserID": null
  },
  {
    "BookID": 90,
    "Title": "Recognia",
    "Author": "Willis Jefferson",
    "ISBN": "2,334",
    "CheckedOut": true,
    "DateDueBck": "",
    "UserID": null
  },
  {
    "BookID": 91,
    "Title": "Calcula",
    "Author": "Melissa Arnold",
    "ISBN": "3,481",
    "CheckedOut": false,
    "DateDueBck": "",
    "UserID": null
  },
  {
    "BookID": 92,
    "Title": "Coriander",
    "Author": "Dunlap Carney",
    "ISBN": "2,670",
    "CheckedOut": false,
    "DateDueBck": "",
    "UserID": null
  },
  {
    "BookID": 93,
    "Title": "Adornica",
    "Author": "Marcia Day",
    "ISBN": "1,810",
    "CheckedOut": false,
    "DateDueBck": "",
    "UserID": null
  },
  {
    "BookID": 94,
    "Title": "Enormo",
    "Author": "Bolton Chavez",
    "ISBN": "1,047",
    "CheckedOut": false,
    "DateDueBck": "",
    "UserID": null
  },
  {
    "BookID": 95,
    "Title": "Jamnation",
    "Author": "Guy Everett",
    "ISBN": "3,002",
    "CheckedOut": false,
    "DateDueBck": "",
    "UserID": null
  }
]